setup.py
openwrt_wac.egg-info/PKG-INFO
openwrt_wac.egg-info/SOURCES.txt
openwrt_wac.egg-info/dependency_links.txt
openwrt_wac.egg-info/entry_points.txt
openwrt_wac.egg-info/requires.txt
openwrt_wac.egg-info/top_level.txt
wac/__init__.py
wac/cmd.py
wac/exception.py
wac/service.py
wac/ubus.py
wac/utils.py