Metadata-Version: 1.1
Name: openwrt-wac
Version: 0.1.1
Summary: a simple command line tool for managing groups of openwrt based rotuers
Home-page: http://github.com/jianingy/openwrt-wac
Author: Jianing Yang
Author-email: jianingy.yang@gmail.com
License: UNKNOWN
Platform: UNKNOWN
Classifier: Development Status :: 4 - Beta
Classifier: Environment :: Console
Classifier: Topic :: Utilities
